pychecktype/__init__.py
pychecktype/_checked_35.py
pychecktype/checked.py
pychecktype-1.4.1.dist-info/LICENSE
pychecktype-1.4.1.dist-info/METADATA
pychecktype-1.4.1.dist-info/WHEEL
pychecktype-1.4.1.dist-info/top_level.txt
pychecktype-1.4.1.dist-info/RECORD
