Metadata-Version: 2.1
Name: pychecktype
Version: 1.4.1
Summary: asyncio wrapper for grpc.io
Home-page: https://github.com/hubo1016/pychecktype
Author: Hu Bo
Author-email: hubo1016@126.com
License: Apache
Platform: any
Classifier: Intended Audience :: Developers
Classifier: Programming Language :: Python
Classifier: Topic :: Software Development
